logreel/__init__.py
logreel/collector/__init__.py
logreel/collector/core.py
logreel/exceptions.py
logreel/logging_config.py
logreel/main.py
logreel/models.py
logreel/plugins/__init__.py
logreel/plugins/factory.py
logreel/plugins/interfaces/__init__.py
logreel/plugins/interfaces/base.py
logreel/plugins/interfaces/destination.py
logreel/plugins/interfaces/source.py
logreel/routes/__init__.py
logreel/routes/health_route.py
logreel/settings.py
logreel/version.py
logreel-0.2.2.dist-info/LICENSE
logreel-0.2.2.dist-info/METADATA
logreel-0.2.2.dist-info/WHEEL
logreel-0.2.2.dist-info/RECORD
