Metadata-Version: 2.3
Name: logreel
Version: 0.2.2
Summary: Application that retrieves logs from systems that aren’t natively supported by Google SecOps
Author: Simone Roma
Author-email: simone.roma@nomios.co.uk
Requires-Python: >=3.12,<4.0
Classifier: Programming Language :: Python :: 3
Classifier: Programming Language :: Python :: 3.12
Classifier: Programming Language :: Python :: 3.13
Requires-Dist: fastapi (>=0.115.3,<0.116.0)
Requires-Dist: pydantic-settings (>=2.6.0,<3.0.0)
Requires-Dist: setuptools (>=75.2.0,<76.0.0)
Requires-Dist: structlog (>=24.4.0,<25.0.0)
Requires-Dist: uvicorn (>=0.32.0,<0.33.0)
